setup.py
simpledistributionsv1/Binomialdistribution.py
simpledistributionsv1/Gaussiandistribution.py
simpledistributionsv1/Generaldistribution.py
simpledistributionsv1/__init__.py
simpledistributionsv1.egg-info/PKG-INFO
simpledistributionsv1.egg-info/SOURCES.txt
simpledistributionsv1.egg-info/dependency_links.txt
simpledistributionsv1.egg-info/not-zip-safe
simpledistributionsv1.egg-info/top_level.txt